AUTHORS
LICENSE
MANIFEST.in
README.rst
setup.py
django_rgallery.egg-info/PKG-INFO
django_rgallery.egg-info/SOURCES.txt
django_rgallery.egg-info/dependency_links.txt
django_rgallery.egg-info/not-zip-safe
django_rgallery.egg-info/requires.txt
django_rgallery.egg-info/top_level.txt
docs/Makefile
docs/source/backends.rst
docs/source/changelog.rst
docs/source/commands.rst
docs/source/conf.py
docs/source/contributing.rst
docs/source/django-rgallery001.png
docs/source/django-rgallery002.png
docs/source/index.rst
docs/source/quickstart.rst
docs/source/settings.rst
docs/source/todo.rst
rgallery/__init__.py
rgallery/admin.py
rgallery/engine.py
rgallery/forms.py
rgallery/models.py
rgallery/tests.py
rgallery/urls.py
rgallery/views.py
rgallery/management/.DS_Store
rgallery/management/__init__.py
rgallery/management/__init__.pyc
rgallery/management/commands/__init__.py
rgallery/management/commands/__init__.pyc
rgallery/management/commands/_images.pyc
rgallery/management/commands/_videos.pyc
rgallery/management/commands/backend_dropbox.py
rgallery/management/commands/backend_dropbox.pyc
rgallery/management/commands/backend_file.py
rgallery/management/commands/backend_file.pyc
rgallery/management/commands/backend_form.py
rgallery/management/commands/backend_form.pyc
rgallery/management/commands/dropbox_auth.pyc
rgallery/management/commands/dropbox_download.pyc
rgallery/management/commands/dropbox_photosync.py
rgallery/management/commands/dropbox_photosync.py.orig
rgallery/management/commands/dropbox_photosync.pyc
rgallery/management/commands/dropbox_videosync.py
rgallery/management/commands/dropbox_videosync.pyc
rgallery/management/commands/imgcache.pyc
rgallery/management/commands/mediasync.py
rgallery/management/commands/mediasync.pyc
rgallery/management/commands/mkthumb.py
rgallery/management/commands/mkthumb.pyc
rgallery/management/commands/parse_photos.pyc
rgallery/management/commands/parse_videos.pyc
rgallery/management/commands/utils.py
rgallery/management/commands/utils.py.orig
rgallery/management/commands/utils.pyc
rgallery/migrations/0001_initial.py
rgallery/migrations/__init__.py
rgallery/static/rgallery/img/ytplay.png
rgallery/static/rgallery/js/custom.js
rgallery/static/rgallery/less/custom.less
