Metadata-Version: 1.0
Name: django-rgallery
Version: 1.8.0
Summary: Yet another Django Gallery App
Home-page: http://bitbucket.org/r0sk/django-rgallery
Author: Oscar M. Lage Guitian
Author-email: info@oscarmlage.com
License: BSD licence, see LICENSE file
Keywords: django application gallery
Platform: UNKNOWN
Classifier: Development Status :: 4 - Beta
Classifier: Environment :: Web Environment
Classifier: Framework :: Django
Classifier: Intended Audience :: Developers
Classifier: License :: OSI Approved :: BSD License
Classifier: Operating System :: OS Independent
Classifier: Programming Language :: Python
Classifier: Topic :: Internet :: WWW/HTTP :: Dynamic Content
Classifier: Topic :: Software Development :: Libraries :: Python Modules
